bottle_inject.py
Bottle_Inject-0.1.3.dist-info/top_level.txt
Bottle_Inject-0.1.3.dist-info/zip-safe
Bottle_Inject-0.1.3.dist-info/metadata.json
Bottle_Inject-0.1.3.dist-info/RECORD
Bottle_Inject-0.1.3.dist-info/DESCRIPTION.rst
Bottle_Inject-0.1.3.dist-info/WHEEL
Bottle_Inject-0.1.3.dist-info/METADATA
