Metadata-Version: 2.0
Name: Bottle-Inject
Version: 0.1.3
Summary: Dependency injection for Bottle.
Home-page: http://github.com/bottlepy/bottle-inject/
Author: Marcel Hellkamp
Author-email: marc@gsites.de
License: MIT
Platform: any
Classifier: Environment :: Web Environment
Classifier: Intended Audience :: Developers
Classifier: License :: OSI Approved :: MIT License
Classifier: Operating System :: OS Independent
Classifier: Programming Language :: Python
Classifier: Topic :: Internet :: WWW/HTTP :: Dynamic Content
Classifier: Topic :: Software Development :: Libraries :: Python Modules
Requires-Dist: distribute
Requires-Dist: bottle (>=0.11)
